main.py
task_5_popkamuravia-1.0.0.dist-info/METADATA
task_5_popkamuravia-1.0.0.dist-info/WHEEL
task_5_popkamuravia-1.0.0.dist-info/top_level.txt
task_5_popkamuravia-1.0.0.dist-info/RECORD
